README.rst
setup.py
gentleman/__init__.py
gentleman/async.py
gentleman/base.py
gentleman/errors.py
gentleman/helpers.py
gentleman/sync.py
gentleman.egg-info/PKG-INFO
gentleman.egg-info/SOURCES.txt
gentleman.egg-info/dependency_links.txt
gentleman.egg-info/top_level.txt