Metadata-Version: 1.0
Name: gentleman
Version: 15.5
Summary: Ganeti RAPI client
Home-page: http://github.com/MostAwesomeDude/gentleman
Author: Corbin Simpson
Author-email: cds@corbinsimpson.com
License: GPLv2 or later
Platform: UNKNOWN
